mitsuba-3.7.1.dist-info/RECORD
mitsuba-3.7.1.dist-info/WHEEL
mitsuba-3.7.1.dist-info/entry_points.txt
mitsuba-3.7.1.dist-info/METADATA
mitsuba-3.7.1.dist-info/licenses/LICENSE
mitsuba/libmitsuba.dylib
mitsuba/quad.pyi
mitsuba/libjpeg-mitsuba.dylib
mitsuba/config.py
mitsuba/llvm_ad_spectral_polarized.cpython-39-darwin.so
mitsuba/llvm_ad_rgb.cpython-39-darwin.so
mitsuba/math.pyi
mitsuba/__init__.pyi
mitsuba/libImath-mitsuba.dylib
mitsuba/libIexMath-mitsuba.dylib
mitsuba/libIex-mitsuba.dylib
mitsuba/llvm_ad_mono_polarized.cpython-39-darwin.so
mitsuba/mueller.pyi
mitsuba/misc.pyi
mitsuba/scalar_rgb.cpython-39-darwin.so
mitsuba/__init__.py
mitsuba/mitsuba_alias.cpython-39-darwin.so
mitsuba/libembree3.dylib
mitsuba/libIlmImfUtil-mitsuba.dylib
mitsuba/detail.pyi
mitsuba/util.pyi
mitsuba/spline.pyi
mitsuba/parser.pyi
mitsuba/libpugixml.dylib
mitsuba/llvm_ad_spectral.cpython-39-darwin.so
mitsuba/warp.pyi
mitsuba/ad.pyi
mitsuba/detail.py
mitsuba/libnanobind-drjit.dylib
mitsuba/scalar_spectral_polarized.cpython-39-darwin.so
mitsuba/scalar_spectral.cpython-39-darwin.so
mitsuba/py.typed
mitsuba/libIlmImf-mitsuba.dylib
mitsuba/llvm_ad_mono.cpython-39-darwin.so
mitsuba/math_py.pyi
mitsuba/libpng-mitsuba.dylib
mitsuba/mitsuba
mitsuba/libIlmThread-mitsuba.dylib
mitsuba/mitsuba_ext.cpython-39-darwin.so
mitsuba/filesystem.pyi
mitsuba/libHalf-mitsuba.dylib
mitsuba/chi2.pyi
mitsuba/cmake/IlmBase/IlmBaseConfigVersion.cmake
mitsuba/cmake/IlmBase/IlmBaseTargets.cmake
mitsuba/cmake/IlmBase/IlmBaseConfig.cmake
mitsuba/cmake/IlmBase/IlmBaseTargets-release.cmake
mitsuba/cmake/OpenEXR/OpenEXRConfigVersion.cmake
mitsuba/cmake/OpenEXR/OpenEXRTargets.cmake
mitsuba/cmake/OpenEXR/OpenEXRConfig.cmake
mitsuba/cmake/OpenEXR/OpenEXRTargets-release.cmake
mitsuba/python/sys_info.py
mitsuba/python/util.py
mitsuba/python/__init__.py
mitsuba/python/tensor_io.py
mitsuba/python/cli.py
mitsuba/python/tonemap.py
mitsuba/python/polvis.py
mitsuba/python/testing.py
mitsuba/python/math_py.py
mitsuba/python/chi2.py
mitsuba/python/ad/projective.py
mitsuba/python/ad/__init__.py
mitsuba/python/ad/optimizers.py
