Metadata-Version: 2.1
Name: mitsuba
Version: 3.7.1
Summary: Mitsuba 3: A Retargetable Forward and Inverse Renderer
Author-Email: Wenzel Jakob <wenzel.jakob@epfl.ch>
Classifier: License :: OSI Approved :: BSD License
Project-URL: Homepage, https://github.com/mitsuba-renderer/mitsuba3
Requires-Python: >=3.9
Requires-Dist: typing_extensions>=4.12; python_version < "3.11"
Requires-Dist: drjit==1.2.0
